setup.py
agent_for_sre/__init__.py
agent_for_sre.egg-info/PKG-INFO
agent_for_sre.egg-info/SOURCES.txt
agent_for_sre.egg-info/dependency_links.txt
agent_for_sre.egg-info/not-zip-safe
agent_for_sre.egg-info/requires.txt
agent_for_sre.egg-info/top_level.txt
agent_for_sre/Collector/Collector.py
agent_for_sre/Collector/DnsCollector.py
agent_for_sre/Collector/EcsMachineCollector.py
agent_for_sre/Collector/FileinfoProcessCollector.py
agent_for_sre/Collector/FirewallCollector.py
agent_for_sre/Collector/MachineInfoCollectoer.py
agent_for_sre/Collector/MachineStatusCollectoer.py
agent_for_sre/Collector/NetinfoProcessCollector.py
agent_for_sre/Collector/NetscalerCollector.py
agent_for_sre/Collector/NginxCollector.py
agent_for_sre/Collector/PhysicalMachineCollector.py
agent_for_sre/Collector/ProcessCollector.py
agent_for_sre/Collector/WafCollector.py
agent_for_sre/Collector/__init__.py
agent_for_sre/Conf/Conf.py
agent_for_sre/Conf/ConfAnalyzer.py
agent_for_sre/Conf/ConfIdcAnalyzer.py
agent_for_sre/Conf/ConfSreAnalyzer.py
agent_for_sre/Conf/__init__.py
agent_for_sre/Monitor/Alert.py
agent_for_sre/Monitor/DnsMonitor.py
agent_for_sre/Monitor/LogMonitor.py
agent_for_sre/Monitor/Monitor.py
agent_for_sre/Monitor/UrlMonitor.py
agent_for_sre/Monitor/__init__.py
agent_for_sre/Monitor/check_network_callmap.py
agent_for_sre/Tools/Activemq.py
agent_for_sre/Tools/Es.py
agent_for_sre/Tools/Kafka.py
agent_for_sre/Tools/__init__.py
cli/check-url-callmap.py
cli/log-monitor.py