Metadata-Version: 1.0
Name: agent-for-sre
Version: 0.0.48
Summary: The agent for sre
Home-page: http://no.website/
Author: niht
Author-email: 5007088@qq.com
License: GPLv3
Platform: UNKNOWN
